pytest_xdist_tracker/__init__.py
pytest_xdist_tracker/_version.py
pytest_xdist_tracker/plugin.py
pytest_xdist_tracker/tracker.py
pytest_xdist_tracker-0.0.2.dist-info/LICENSE
pytest_xdist_tracker-0.0.2.dist-info/METADATA
pytest_xdist_tracker-0.0.2.dist-info/WHEEL
pytest_xdist_tracker-0.0.2.dist-info/entry_points.txt
pytest_xdist_tracker-0.0.2.dist-info/top_level.txt
pytest_xdist_tracker-0.0.2.dist-info/RECORD
